aws_credentialer/__init__.py
aws_credentialer/__main__.py
aws_credentialer-0.1.2.dist-info/LICENSE
aws_credentialer-0.1.2.dist-info/METADATA
aws_credentialer-0.1.2.dist-info/WHEEL
aws_credentialer-0.1.2.dist-info/top_level.txt
aws_credentialer-0.1.2.dist-info/RECORD
