Metadata-Version: 2.1
Name: aws-credentialer
Version: 0.1.2
Summary: An AWS MFA Credentials Updater
Author-email: Hidayatullah Ahsan <hahsan@techicon.net>
Project-URL: Homepage, https://github.com/hahsan-ti/aws-credentialer
Project-URL: Bug Tracker, https://github.com/hahsan-ti/aws-credentialer/issues
Classifier: Programming Language :: Python :: 3
Classifier: License :: OSI Approved :: MIT License
Classifier: Operating System :: OS Independent
Requires-Python: >=3.9
License-File: LICENSE
Requires-Dist: boto3 (==1.26.110)
Requires-Dist: botocore (==1.29.110)
Requires-Dist: jmespath (==1.0.1)
Requires-Dist: python-dateutil (==2.8.2)
Requires-Dist: s3transfer (==0.6.0)
Requires-Dist: six (==1.16.0)
Requires-Dist: urllib3 (==1.26.15)
